{
    "id": "rct2.surface.sand",
    "authors": ["Chris Sawyer", "Simon Foster"],
    "version": "1.0",
    "originalId": "0000008B|#RCT2SSA|00000000",
    "sourceGame": ["rct2", "rct1"],
    "objectType": "terrain_surface",
    "properties": {
        "price": 110,
        "smoothWithSelf": true,
        "smoothWithOther": true
    },
    "images": [
        "$G1[5592]",
        "$G1[28965..28970]",
        "$G1[1972..2028]"
    ],
    "strings": {
        "name": {
            "en-GB": "Sand",
            "de-DE": "Sand",
            "nl-NL": "Zand",
            "pt-BR": "Areia",
            "ja-JP": "砂",
            "fr-FR": "Sable",
            "ar-EG": "رمل",
            "ca-ES": "Sorra",
            "cs-CZ": "Písek",
            "da-DK": "Sand",
            "es-ES": "Arena",
            "fi-FI": "Hiekka",
            "hu-HU": "Homok",
            "it-IT": "Sabbia",
            "ja-JP": "砂",
            "ko-KR": "모래",
            "pl-PL": "Piach",
            "sv-SE": "Sand",
            "tr-TR": "Kum",
            "zh-CN": "沙地",
            "zh-TW": "沙地"
        }
    }
}
